bchosttrust/__init__.py
bchosttrust/__main__.py
bchosttrust/attitudes.py
bchosttrust/exceptions.py
bchosttrust/utils.py
bchosttrust/analysis/__init__.py
bchosttrust/analysis/horizontal.py
bchosttrust/analysis/search.py
bchosttrust/analysis/tree.py
bchosttrust/cli/__init__.py
bchosttrust/cli/create.py
bchosttrust/cli/get.py
bchosttrust/cli/get_rate.py
bchosttrust/cli/import_block.py
bchosttrust/cli/similar_domain.py
bchosttrust/cli/tree.py
bchosttrust/consensus/__init__.py
bchosttrust/consensus/limitations.py
bchosttrust/consensus/powc.py
bchosttrust/internal/__init__.py
bchosttrust/internal/block.py
bchosttrust/storage/__init__.py
bchosttrust/storage/dummy.py
bchosttrust/storage/import_block.py
bchosttrust/storage/leveldb.py
bchosttrust/storage/meta.py
bchosttrust-0.0.4.dist-info/LICENSE.txt
bchosttrust-0.0.4.dist-info/METADATA
bchosttrust-0.0.4.dist-info/WHEEL
bchosttrust-0.0.4.dist-info/entry_points.txt
bchosttrust-0.0.4.dist-info/top_level.txt
bchosttrust-0.0.4.dist-info/RECORD
