Metadata-Version: 2.1
Name: bchosttrust
Version: 0.0.4
Summary: Blockchain solution to domain name trustworthy
Author-email: Cato Yiu <root@1f616emo.xyz>, Marco Pui <marcopui5507@gmail.com>, Lewis Chen <bestnoodles101@gmail.com>, bchosttrust@1f616emo.xyz
Classifier: Development Status :: 2 - Pre-Alpha
Classifier: License :: OSI Approved :: GNU Lesser General Public License v3 or later (LGPLv3+)
Classifier: Intended Audience :: Developers
Classifier: Topic :: System :: Networking
Classifier: Environment :: Web Environment
Classifier: Programming Language :: Python :: 3
Classifier: Programming Language :: Python :: 3.11
Requires-Python: ==3.11.*
License-File: LICENSE.txt
Requires-Dist: anytree ==2.12.1
Requires-Dist: click ==8.1.7
Requires-Dist: lazy-loader ==0.3
Requires-Dist: plyvel ==1.5.0
Requires-Dist: typeguard ==4.1.5
